pau_cuda.cpython-38-x86_64-linux-gnu.so
pau/__init__.py
pau/find_init_weights.py
pau/get_weights.py
pau/paus_config.json
pau/paus_py.py
pau/utils.py
pau.libs/libcudart.so.10.2.89
pau_keras/__init__.py
pau_keras/pade_activation_unit.py
pau_keras/pade_keras_functions.py
pau_keras/test_tfkeras.py
pau_torch/__init__.py
pau_torch/pade_activation_unit.py
pau_torch/pade_cuda_functions.py
pau_torch/pade_pytorch_functions.py
pau_torch/test_torch.py
pau-0.0.17.dist-info/METADATA
pau-0.0.17.dist-info/WHEEL
pau-0.0.17.dist-info/top_level.txt
pau-0.0.17.dist-info/RECORD
