Metadata-Version: 2.1
Name: pau
Version: 0.0.17
Summary: Pade Activation Unit
Home-page: https://github.com/ml-research/pau
Author: Alejandro Molina, Quentin Delfosse, Patrick Schramowski
Author-email: molina@cs.tu-darmstadt.de, quentin.delfosse@cs.tu-darmstadt.de
License: UNKNOWN
Platform: UNKNOWN
Classifier: Programming Language :: Python :: 3
Classifier: Programming Language :: Python :: 3.6
Classifier: Programming Language :: Python :: 3.7
Classifier: Programming Language :: Python :: 3.8
Classifier: License :: OSI Approved :: Apache Software License
Requires-Python: >=3.5.0
Requires-Dist: torch (==1.5.0)
